aind_msma_utils/__init__.py
aind_msma_utils/exaspim/__init__.py
aind_msma_utils/exaspim/models.py
aind_msma_utils/exaspim/sharepoint_generator.py
aind_msma_utils-0.0.5.dist-info/LICENSE
aind_msma_utils-0.0.5.dist-info/METADATA
aind_msma_utils-0.0.5.dist-info/WHEEL
aind_msma_utils-0.0.5.dist-info/top_level.txt
aind_msma_utils-0.0.5.dist-info/RECORD
