Metadata-Version: 2.1
Name: aind-msma-utils
Version: 0.0.5
Summary: Generated from aind-library-template
Author: Allen Institute for Neural Dynamics
License: MIT
Classifier: Programming Language :: Python :: 3
Requires-Python: >=3.10
License-File: LICENSE
Requires-Dist: aind-data-schema >=1.0.0
Requires-Dist: aind-data-schema-models ==0.4.4
Requires-Dist: aind-smartsheet-api ==0.1.1
Requires-Dist: openpyxl
Requires-Dist: pydantic-settings >=2.0
Requires-Dist: pandas
Requires-Dist: numpy
Requires-Dist: pytz
Provides-Extra: dev
Requires-Dist: black ; extra == 'dev'
Requires-Dist: coverage ; extra == 'dev'
Requires-Dist: flake8 ; extra == 'dev'
Requires-Dist: interrogate ; extra == 'dev'
Requires-Dist: isort ; extra == 'dev'
Requires-Dist: Sphinx ; extra == 'dev'
Requires-Dist: furo ; extra == 'dev'
